llama_index/tools/playwright/__init__.py
llama_index/tools/playwright/base.py
llama_index_tools_playwright-0.3.1.dist-info/METADATA
llama_index_tools_playwright-0.3.1.dist-info/WHEEL
llama_index_tools_playwright-0.3.1.dist-info/licenses/LICENSE
llama_index_tools_playwright-0.3.1.dist-info/RECORD
