Metadata-Version: 2.4
Name: llama-index-tools-playwright
Version: 0.3.1
Summary: llama-index tools playwright integration
Author-email: Your Name <you@example.com>
License-Expression: MIT
License-File: LICENSE
Requires-Python: <4.0,>=3.9
Requires-Dist: beautifulsoup4<5,>=4.12.2
Requires-Dist: llama-index-core<0.15,>=0.13.0
Requires-Dist: playwright<2,>=1.49.1
